frequenz/client/conftest.py
frequenz/client/dispatch/__init__.py
frequenz/client/dispatch/__main__.py
frequenz/client/dispatch/_cli_types.py
frequenz/client/dispatch/_client.py
frequenz/client/dispatch/_internal_types.py
frequenz/client/dispatch/py.typed
frequenz/client/dispatch/recurrence.py
frequenz/client/dispatch/types.py
frequenz/client/dispatch/test/__init__.py
frequenz/client/dispatch/test/_service.py
frequenz/client/dispatch/test/client.py
frequenz/client/dispatch/test/fixtures.py
frequenz/client/dispatch/test/generator.py
frequenz_client_dispatch-1.0.0.dist-info/licenses/LICENSE
frequenz_client_dispatch-1.0.0.dist-info/METADATA
frequenz_client_dispatch-1.0.0.dist-info/WHEEL
frequenz_client_dispatch-1.0.0.dist-info/entry_points.txt
frequenz_client_dispatch-1.0.0.dist-info/top_level.txt
frequenz_client_dispatch-1.0.0.dist-info/RECORD
